[
  {
    "name": "between_broadsword",
    "type": "tool",
    "data": "tools/between_broadsword.json"
  },
  {
    "name": "between_pickaxe",
    "type": "tool",
    "data": "tools/between_pickaxe.json"
  },
  {
    "name": "between_hatchet",
    "type": "tool",
    "data": "tools/between_hatchet.json"
  },
  {
    "name": "between_shovel",
    "type": "tool",
    "data": "tools/between_shovel.json"
  },
  {
    "name": "between_shortbow",
    "type": "tool",
    "data": "tools/between_shortbow.json"
  }
]